[
  {
    "framework": "actix",
    "language": "Rust",
    "rps": 99895,
    "avg_latency": "8.11ms",
    "p99_latency": "14.40ms",
    "cpu": "3819.6%",
    "memory": "116.1MiB",
    "connections": 1024,
    "threads": 64,
    "duration": "5s",
    "pipeline": 1,
    "bandwidth": "789.09MB/s",
    "input_bw": "",
    "reconnects": 201,
    "status_2xx": 998956,
    "status_3xx": 0,
    "status_4xx": 0,
    "status_5xx": 0
  },
  {
    "framework": "aspnet-minimal",
    "language": "C#",
    "rps": 132460,
    "avg_latency": "3.68ms",
    "p99_latency": "11.80ms",
    "cpu": "3610.4%",
    "memory": "300.8MiB",
    "connections": 1024,
    "threads": 64,
    "duration": "5s",
    "pipeline": 1,
    "bandwidth": "1.03GB/s",
    "input_bw": "",
    "reconnects": 0,
    "status_2xx": 1324607,
    "status_3xx": 0,
    "status_4xx": 0,
    "status_5xx": 0
  },
  {
    "framework": "aspnet-mvc",
    "language": "C#",
    "rps": 128881,
    "avg_latency": "4.09ms",
    "p99_latency": "12.50ms",
    "cpu": "3816.8%",
    "memory": "314.1MiB",
    "connections": 1024,
    "threads": 64,
    "duration": "5s",
    "pipeline": 1,
    "bandwidth": "1.00GB/s",
    "input_bw": "",
    "reconnects": 0,
    "status_2xx": 1288819,
    "status_3xx": 0,
    "status_4xx": 0,
    "status_5xx": 0
  },
  {
    "framework": "bun",
    "language": "TS",
    "rps": 128208,
    "avg_latency": "5.50ms",
    "p99_latency": "23.50ms",
    "cpu": "5170.3%",
    "memory": "4.8GiB",
    "connections": 1024,
    "threads": 64,
    "duration": "5s",
    "pipeline": 1,
    "bandwidth": "1010.06MB/s",
    "input_bw": "",
    "reconnects": 0,
    "status_2xx": 1282082,
    "status_3xx": 0,
    "status_4xx": 0,
    "status_5xx": 0
  },
  {
    "framework": "carno",
    "language": "TS",
    "rps": 127652,
    "avg_latency": "5.47ms",
    "p99_latency": "24.00ms",
    "cpu": "5182.5%",
    "memory": "4.4GiB",
    "connections": 1024,
    "threads": 64,
    "duration": "5s",
    "pipeline": 1,
    "bandwidth": "1005.74MB/s",
    "input_bw": "",
    "reconnects": 0,
    "status_2xx": 1276520,
    "status_3xx": 0,
    "status_4xx": 0,
    "status_5xx": 0
  },
  {
    "framework": "chi",
    "language": "Go",
    "rps": 31802,
    "avg_latency": "29.97ms",
    "p99_latency": "65.30ms",
    "cpu": "3981.6%",
    "memory": "244.2MiB",
    "connections": 1024,
    "threads": 64,
    "duration": "5s",
    "pipeline": 1,
    "bandwidth": "251.44MB/s",
    "input_bw": "",
    "reconnects": 0,
    "status_2xx": 318022,
    "status_3xx": 0,
    "status_4xx": 0,
    "status_5xx": 0
  },
  {
    "framework": "deno",
    "language": "TS",
    "rps": 70532,
    "avg_latency": "11.79ms",
    "p99_latency": "18.20ms",
    "cpu": "6066.6%",
    "memory": "3.3GiB",
    "connections": 1024,
    "threads": 64,
    "duration": "5s",
    "pipeline": 1,
    "bandwidth": "558.19MB/s",
    "input_bw": "",
    "reconnects": 0,
    "status_2xx": 705329,
    "status_3xx": 0,
    "status_4xx": 0,
    "status_5xx": 0
  },
  {
    "framework": "django",
    "language": "Python",
    "rps": 35477,
    "avg_latency": "26.78ms",
    "p99_latency": "28.30ms",
    "cpu": "5031.3%",
    "memory": "2.6GiB",
    "connections": 1024,
    "threads": 64,
    "duration": "5s",
    "pipeline": 1,
    "bandwidth": "315.99MB/s",
    "input_bw": "",
    "reconnects": 354903,
    "status_2xx": 354773,
    "status_3xx": 0,
    "status_4xx": 0,
    "status_5xx": 0
  },
  {
    "framework": "echo",
    "language": "Go",
    "rps": 30688,
    "avg_latency": "31.11ms",
    "p99_latency": "66.20ms",
    "cpu": "3933.0%",
    "memory": "221.6MiB",
    "connections": 1024,
    "threads": 64,
    "duration": "5s",
    "pipeline": 1,
    "bandwidth": "242.67MB/s",
    "input_bw": "",
    "reconnects": 0,
    "status_2xx": 306880,
    "status_3xx": 0,
    "status_4xx": 0,
    "status_5xx": 0
  },
  {
    "framework": "elysia",
    "language": "TS",
    "rps": 127638,
    "avg_latency": "5.48ms",
    "p99_latency": "24.10ms",
    "cpu": "5227.2%",
    "memory": "5.7GiB",
    "connections": 1024,
    "threads": 64,
    "duration": "5s",
    "pipeline": 1,
    "bandwidth": "1005.63MB/s",
    "input_bw": "",
    "reconnects": 0,
    "status_2xx": 1276384,
    "status_3xx": 0,
    "status_4xx": 0,
    "status_5xx": 0
  },
  {
    "framework": "express",
    "language": "JS",
    "rps": 90703,
    "avg_latency": "8.46ms",
    "p99_latency": "16.30ms",
    "cpu": "6069.7%",
    "memory": "5.8GiB",
    "connections": 1024,
    "threads": 64,
    "duration": "5s",
    "pipeline": 1,
    "bandwidth": "727.26MB/s",
    "input_bw": "",
    "reconnects": 119,
    "status_2xx": 907032,
    "status_3xx": 0,
    "status_4xx": 0,
    "status_5xx": 0
  },
  {
    "framework": "fastapi",
    "language": "Python",
    "rps": 72926,
    "avg_latency": "11.29ms",
    "p99_latency": "28.10ms",
    "cpu": "5261.5%",
    "memory": "2.3GiB",
    "connections": 1024,
    "threads": 64,
    "duration": "5s",
    "pipeline": 1,
    "bandwidth": "577.35MB/s",
    "input_bw": "",
    "reconnects": 0,
    "status_2xx": 729264,
    "status_3xx": 0,
    "status_4xx": 0,
    "status_5xx": 0
  },
  {
    "framework": "fastify",
    "language": "JS",
    "rps": 129202,
    "avg_latency": "5.09ms",
    "p99_latency": "9.27ms",
    "cpu": "5734.1%",
    "memory": "3.7GiB",
    "connections": 1024,
    "threads": 64,
    "duration": "5s",
    "pipeline": 1,
    "bandwidth": "1.00GB/s",
    "input_bw": "",
    "reconnects": 0,
    "status_2xx": 1292024,
    "status_3xx": 0,
    "status_4xx": 0,
    "status_5xx": 0
  },
  {
    "framework": "fastpysgi-asgi",
    "language": "Python",
    "rps": 106011,
    "avg_latency": "7.07ms",
    "p99_latency": "37.70ms",
    "cpu": "5976.5%",
    "memory": "894.1MiB",
    "connections": 1024,
    "threads": 64,
    "duration": "5s",
    "pipeline": 1,
    "bandwidth": "840.60MB/s",
    "input_bw": "",
    "reconnects": 0,
    "status_2xx": 1060118,
    "status_3xx": 0,
    "status_4xx": 0,
    "status_5xx": 0
  },
  {
    "framework": "fastpysgi-wsgi",
    "language": "Python",
    "rps": 60335,
    "avg_latency": "14.04ms",
    "p99_latency": "25.00ms",
    "cpu": "4125.0%",
    "memory": "625.9MiB",
    "connections": 1024,
    "threads": 64,
    "duration": "5s",
    "pipeline": 1,
    "bandwidth": "478.42MB/s",
    "input_bw": "",
    "reconnects": 0,
    "status_2xx": 603359,
    "status_3xx": 0,
    "status_4xx": 0,
    "status_5xx": 0
  },
  {
    "framework": "fiber",
    "language": "Go",
    "rps": 34529,
    "avg_latency": "27.66ms",
    "p99_latency": "62.80ms",
    "cpu": "3745.1%",
    "memory": "190.9MiB",
    "connections": 1024,
    "threads": 64,
    "duration": "5s",
    "pipeline": 1,
    "bandwidth": "272.45MB/s",
    "input_bw": "",
    "reconnects": 0,
    "status_2xx": 345295,
    "status_3xx": 0,
    "status_4xx": 0,
    "status_5xx": 0
  },
  {
    "framework": "flask",
    "language": "Python",
    "rps": 37198,
    "avg_latency": "25.59ms",
    "p99_latency": "27.30ms",
    "cpu": "4934.0%",
    "memory": "2.3GiB",
    "connections": 1024,
    "threads": 64,
    "duration": "5s",
    "pipeline": 1,
    "bandwidth": "330.52MB/s",
    "input_bw": "",
    "reconnects": 371993,
    "status_2xx": 371988,
    "status_3xx": 0,
    "status_4xx": 0,
    "status_5xx": 0
  },
  {
    "framework": "fletch",
    "language": "Dart",
    "rps": 2833,
    "avg_latency": "273.83ms",
    "p99_latency": "1.31s",
    "cpu": "761.7%",
    "memory": "838.5MiB",
    "connections": 1024,
    "threads": 64,
    "duration": "5s",
    "pipeline": 1,
    "bandwidth": "22.49MB/s",
    "input_bw": "",
    "reconnects": 0,
    "status_2xx": 28339,
    "status_3xx": 0,
    "status_4xx": 0,
    "status_5xx": 0
  },
  {
    "framework": "genhttp",
    "language": "C#",
    "rps": 147082,
    "avg_latency": "4.33ms",
    "p99_latency": "14.00ms",
    "cpu": "3949.3%",
    "memory": "2.2GiB",
    "connections": 1024,
    "threads": 64,
    "duration": "5s",
    "pipeline": 1,
    "bandwidth": "1.14GB/s",
    "input_bw": "",
    "reconnects": 0,
    "status_2xx": 1470820,
    "status_3xx": 0,
    "status_4xx": 0,
    "status_5xx": 0
  },
  {
    "framework": "gin",
    "language": "Go",
    "rps": 30837,
    "avg_latency": "31.00ms",
    "p99_latency": "68.40ms",
    "cpu": "3947.9%",
    "memory": "228.1MiB",
    "connections": 1024,
    "threads": 64,
    "duration": "5s",
    "pipeline": 1,
    "bandwidth": "243.81MB/s",
    "input_bw": "",
    "reconnects": 0,
    "status_2xx": 308377,
    "status_3xx": 0,
    "status_4xx": 0,
    "status_5xx": 0
  },
  {
    "framework": "go-fasthttp",
    "language": "Go",
    "rps": 34419,
    "avg_latency": "27.76ms",
    "p99_latency": "64.20ms",
    "cpu": "3291.5%",
    "memory": "236.6MiB",
    "connections": 1024,
    "threads": 64,
    "duration": "5s",
    "pipeline": 1,
    "bandwidth": "271.77MB/s",
    "input_bw": "",
    "reconnects": 0,
    "status_2xx": 344198,
    "status_3xx": 0,
    "status_4xx": 0,
    "status_5xx": 0
  },
  {
    "framework": "helidon",
    "language": "Java",
    "rps": 14681,
    "avg_latency": "64.64ms",
    "p99_latency": "160.90ms",
    "cpu": "733.5%",
    "memory": "25.7GiB",
    "connections": 1024,
    "threads": 64,
    "duration": "5s",
    "pipeline": 1,
    "bandwidth": "116.86MB/s",
    "input_bw": "",
    "reconnects": 0,
    "status_2xx": 146812,
    "status_3xx": 0,
    "status_4xx": 0,
    "status_5xx": 0
  },
  {
    "framework": "hono",
    "language": "JS",
    "rps": 129770,
    "avg_latency": "5.29ms",
    "p99_latency": "9.04ms",
    "cpu": "5953.1%",
    "memory": "3.6GiB",
    "connections": 1024,
    "threads": 64,
    "duration": "5s",
    "pipeline": 1,
    "bandwidth": "1.01GB/s",
    "input_bw": "",
    "reconnects": 207,
    "status_2xx": 1297707,
    "status_3xx": 0,
    "status_4xx": 0,
    "status_5xx": 0
  },
  {
    "framework": "hono-bun",
    "language": "TS",
    "rps": 124577,
    "avg_latency": "5.68ms",
    "p99_latency": "24.70ms",
    "cpu": "5218.5%",
    "memory": "4.6GiB",
    "connections": 1024,
    "threads": 64,
    "duration": "5s",
    "pipeline": 1,
    "bandwidth": "983.63MB/s",
    "input_bw": "",
    "reconnects": 0,
    "status_2xx": 1245771,
    "status_3xx": 0,
    "status_4xx": 0,
    "status_5xx": 0
  },
  {
    "framework": "humming-bird",
    "language": "Swift",
    "rps": 9557,
    "avg_latency": "92.36ms",
    "p99_latency": "104.50ms",
    "cpu": "6200.4%",
    "memory": "89.0MiB",
    "connections": 1024,
    "threads": 64,
    "duration": "5s",
    "pipeline": 1,
    "bandwidth": "75.46MB/s",
    "input_bw": "",
    "reconnects": 0,
    "status_2xx": 95577,
    "status_3xx": 0,
    "status_4xx": 0,
    "status_5xx": 0
  },
  {
    "framework": "koa",
    "language": "JS",
    "rps": 128867,
    "avg_latency": "5.37ms",
    "p99_latency": "8.67ms",
    "cpu": "6013.1%",
    "memory": "3.6GiB",
    "connections": 1024,
    "threads": 64,
    "duration": "5s",
    "pipeline": 1,
    "bandwidth": "1022.68MB/s",
    "input_bw": "",
    "reconnects": 195,
    "status_2xx": 1288675,
    "status_3xx": 0,
    "status_4xx": 0,
    "status_5xx": 0
  },
  {
    "framework": "ktor",
    "language": "Kotlin",
    "rps": 141921,
    "avg_latency": "4.67ms",
    "p99_latency": "8.48ms",
    "cpu": "3683.4%",
    "memory": "10.9GiB",
    "connections": 1024,
    "threads": 64,
    "duration": "5s",
    "pipeline": 1,
    "bandwidth": "1.09GB/s",
    "input_bw": "",
    "reconnects": 0,
    "status_2xx": 1419219,
    "status_3xx": 0,
    "status_4xx": 0,
    "status_5xx": 0
  },
  {
    "framework": "nginx-openresty",
    "language": "Lua",
    "rps": 70674,
    "avg_latency": "10.95ms",
    "p99_latency": "277.00ms",
    "cpu": "2504.1%",
    "memory": "2.0GiB",
    "connections": 1024,
    "threads": 64,
    "duration": "5s",
    "pipeline": 1,
    "bandwidth": "546.41MB/s",
    "input_bw": "",
    "reconnects": 0,
    "status_2xx": 706741,
    "status_3xx": 0,
    "status_4xx": 0,
    "status_5xx": 0
  },
  {
    "framework": "ngx-php",
    "language": "PHP",
    "rps": 160354,
    "avg_latency": "3.86ms",
    "p99_latency": "12.00ms",
    "cpu": "4023.2%",
    "memory": "6.2GiB",
    "connections": 1024,
    "threads": 64,
    "duration": "5s",
    "pipeline": 1,
    "bandwidth": "1.24GB/s",
    "input_bw": "",
    "reconnects": 0,
    "status_2xx": 1603549,
    "status_3xx": 0,
    "status_4xx": 0,
    "status_5xx": 0
  },
  {
    "framework": "node",
    "language": "JS",
    "rps": 137177,
    "avg_latency": "4.65ms",
    "p99_latency": "8.31ms",
    "cpu": "5920.5%",
    "memory": "3.4GiB",
    "connections": 1024,
    "threads": 64,
    "duration": "5s",
    "pipeline": 1,
    "bandwidth": "1.06GB/s",
    "input_bw": "",
    "reconnects": 0,
    "status_2xx": 1371773,
    "status_3xx": 0,
    "status_4xx": 0,
    "status_5xx": 0
  },
  {
    "framework": "ntex-tokio",
    "language": "Rust",
    "rps": 101083,
    "avg_latency": "7.82ms",
    "p99_latency": "14.30ms",
    "cpu": "3811.4%",
    "memory": "100.9MiB",
    "connections": 1024,
    "threads": 64,
    "duration": "5s",
    "pipeline": 1,
    "bandwidth": "798.37MB/s",
    "input_bw": "",
    "reconnects": 164,
    "status_2xx": 1010834,
    "status_3xx": 0,
    "status_4xx": 0,
    "status_5xx": 0
  },
  {
    "framework": "phoenix",
    "language": "Elixir",
    "rps": 33810,
    "avg_latency": "27.05ms",
    "p99_latency": "35.00ms",
    "cpu": "3209.6%",
    "memory": "523.6MiB",
    "connections": 1024,
    "threads": 64,
    "duration": "5s",
    "pipeline": 1,
    "bandwidth": "268.78MB/s",
    "input_bw": "",
    "reconnects": 59,
    "status_2xx": 338102,
    "status_3xx": 0,
    "status_4xx": 0,
    "status_5xx": 0
  },
  {
    "framework": "quarkus-jvm",
    "language": "Java",
    "rps": 90703,
    "avg_latency": "8.65ms",
    "p99_latency": "55.90ms",
    "cpu": "3398.7%",
    "memory": "10.1GiB",
    "connections": 1024,
    "threads": 64,
    "duration": "5s",
    "pipeline": 1,
    "bandwidth": "713.76MB/s",
    "input_bw": "",
    "reconnects": 0,
    "status_2xx": 907035,
    "status_3xx": 0,
    "status_4xx": 0,
    "status_5xx": 0
  },
  {
    "framework": "rage",
    "language": "Ruby",
    "rps": 2339,
    "avg_latency": "277.93ms",
    "p99_latency": "1.66s",
    "cpu": "271.0%",
    "memory": "5.1GiB",
    "connections": 1024,
    "threads": 64,
    "duration": "5s",
    "pipeline": 1,
    "bandwidth": "406.60KB/s",
    "input_bw": "",
    "reconnects": 0,
    "status_2xx": 23396,
    "status_3xx": 0,
    "status_4xx": 0,
    "status_5xx": 0
  },
  {
    "framework": "rails",
    "language": "Ruby",
    "rps": 58801,
    "avg_latency": "14.54ms",
    "p99_latency": "34.70ms",
    "cpu": "6457.3%",
    "memory": "5.3GiB",
    "connections": 1024,
    "threads": 64,
    "duration": "5s",
    "pipeline": 1,
    "bandwidth": "469.71MB/s",
    "input_bw": "",
    "reconnects": 40,
    "status_2xx": 588019,
    "status_3xx": 0,
    "status_4xx": 0,
    "status_5xx": 0
  },
  {
    "framework": "roda",
    "language": "Ruby",
    "rps": 92048,
    "avg_latency": "8.45ms",
    "p99_latency": "26.20ms",
    "cpu": "5611.9%",
    "memory": "3.2GiB",
    "connections": 1024,
    "threads": 64,
    "duration": "5s",
    "pipeline": 1,
    "bandwidth": "769.35MB/s",
    "input_bw": "",
    "reconnects": 429,
    "status_2xx": 920486,
    "status_3xx": 0,
    "status_4xx": 0,
    "status_5xx": 0
  },
  {
    "framework": "servicestack",
    "language": "C#",
    "rps": 18252,
    "avg_latency": "49.75ms",
    "p99_latency": "122.10ms",
    "cpu": "767.7%",
    "memory": "368.9MiB",
    "connections": 1024,
    "threads": 64,
    "duration": "5s",
    "pipeline": 1,
    "bandwidth": "145.88MB/s",
    "input_bw": "",
    "reconnects": 0,
    "status_2xx": 182528,
    "status_3xx": 0,
    "status_4xx": 0,
    "status_5xx": 0
  },
  {
    "framework": "simplew",
    "language": "C#",
    "rps": 146887,
    "avg_latency": "4.43ms",
    "p99_latency": "13.30ms",
    "cpu": "3530.8%",
    "memory": "351.8MiB",
    "connections": 1024,
    "threads": 64,
    "duration": "5s",
    "pipeline": 1,
    "bandwidth": "1.14GB/s",
    "input_bw": "",
    "reconnects": 0,
    "status_2xx": 1468875,
    "status_3xx": 0,
    "status_4xx": 0,
    "status_5xx": 0
  },
  {
    "framework": "sinatra",
    "language": "Ruby",
    "rps": 84529,
    "avg_latency": "9.43ms",
    "p99_latency": "26.30ms",
    "cpu": "5941.3%",
    "memory": "3.7GiB",
    "connections": 1024,
    "threads": 64,
    "duration": "5s",
    "pipeline": 1,
    "bandwidth": "664.77MB/s",
    "input_bw": "",
    "reconnects": 298,
    "status_2xx": 845291,
    "status_3xx": 0,
    "status_4xx": 0,
    "status_5xx": 0
  },
  {
    "framework": "sisk",
    "language": "C#",
    "rps": 41,
    "avg_latency": "207.50ms",
    "p99_latency": "381.60ms",
    "cpu": "43.8%",
    "memory": "135.5MiB",
    "connections": 1024,
    "threads": 64,
    "duration": "5s",
    "pipeline": 1,
    "bandwidth": "332.62KB/s",
    "input_bw": "",
    "reconnects": 0,
    "status_2xx": 411,
    "status_3xx": 0,
    "status_4xx": 0,
    "status_5xx": 0
  },
  {
    "framework": "spring-jvm",
    "language": "Java",
    "rps": 84883,
    "avg_latency": "10.94ms",
    "p99_latency": "51.60ms",
    "cpu": "3558.7%",
    "memory": "3.7GiB",
    "connections": 1024,
    "threads": 64,
    "duration": "5s",
    "pipeline": 1,
    "bandwidth": "672.40MB/s",
    "input_bw": "",
    "reconnects": 8036,
    "status_2xx": 848834,
    "status_3xx": 0,
    "status_4xx": 0,
    "status_5xx": 0
  },
  {
    "framework": "starlette",
    "language": "Python",
    "rps": 77255,
    "avg_latency": "10.60ms",
    "p99_latency": "25.30ms",
    "cpu": "5205.0%",
    "memory": "1.7GiB",
    "connections": 1024,
    "threads": 64,
    "duration": "5s",
    "pipeline": 1,
    "bandwidth": "611.76MB/s",
    "input_bw": "",
    "reconnects": 0,
    "status_2xx": 772550,
    "status_3xx": 0,
    "status_4xx": 0,
    "status_5xx": 0
  },
  {
    "framework": "ultimate-express",
    "language": "JS",
    "rps": 128975,
    "avg_latency": "5.36ms",
    "p99_latency": "15.80ms",
    "cpu": "5288.8%",
    "memory": "3.9GiB",
    "connections": 1024,
    "threads": 64,
    "duration": "5s",
    "pipeline": 1,
    "bandwidth": "1.00GB/s",
    "input_bw": "",
    "reconnects": 0,
    "status_2xx": 1289756,
    "status_3xx": 0,
    "status_4xx": 0,
    "status_5xx": 0
  },
  {
    "framework": "workerman",
    "language": "PHP",
    "rps": 137415,
    "avg_latency": "4.92ms",
    "p99_latency": "12.90ms",
    "cpu": "2832.9%",
    "memory": "928.2MiB",
    "connections": 1024,
    "threads": 64,
    "duration": "5s",
    "pipeline": 1,
    "bandwidth": "1.06GB/s",
    "input_bw": "",
    "reconnects": 0,
    "status_2xx": 1374155,
    "status_3xx": 0,
    "status_4xx": 0,
    "status_5xx": 0
  }
]